rconfig/__init__.py
rconfig/cli.py
rconfig/utils.py
python_rconfig-20.2.7.dist-info/LICENSE
python_rconfig-20.2.7.dist-info/METADATA
python_rconfig-20.2.7.dist-info/WHEEL
python_rconfig-20.2.7.dist-info/entry_points.txt
python_rconfig-20.2.7.dist-info/RECORD
