Metadata-Version: 2.1
Name: python-rconfig
Version: 20.2.7
Summary: Helps bring configuration, stored remotely on a ``Consul`` server, to  your application
Home-page: https://github.com/x-amer-ngmx/python-rconfig
License: MIT
Keywords: configurations,settings,consul,env,python,environment-variables,configuration-managment
Author: Artem Angelchev
Author-email: artangelchev@gmail.com
Requires-Python: >=3.6,<4
Classifier: Environment :: Web Environment
Classifier: Intended Audience :: Developers
Classifier: Intended Audience :: System Administrators
Classifier: License :: OSI Approved :: MIT License
Classifier: Operating System :: OS Independent
Classifier: Programming Language :: Python
Classifier: Programming Language :: Python :: 3
Classifier: Programming Language :: Python :: 3.6
Classifier: Programming Language :: Python :: 3.7
Classifier: Programming Language :: Python :: 3.8
Classifier: Programming Language :: Python :: 3.9
Classifier: Programming Language :: Python :: 3.10
Classifier: Programming Language :: Python :: 3.11
Classifier: Programming Language :: Python :: 3.12
Classifier: Topic :: System :: Systems Administration
Classifier: Topic :: Utilities
Provides-Extra: cli
Provides-Extra: yaml
Requires-Dist: click (>=8.0,<9.0) ; extra == "cli"
Requires-Dist: python-consul (>=1.1.0,<2.0.0)
Requires-Dist: pyyaml (>=5.3,<6.0) ; extra == "yaml"
Project-URL: Repository, https://github.com/x-amer-ngmx/python-rconfig
